{
  "kimchi-grilled-cheese": "bb022076313af28c",
  "smashed-avocado-toast": "e7ae25d6936f6291",
  "ciabatta-grilled-vegetables": "5852195ca6f8196f",
  "toast-champignon-labneh": "45a3750c5770e9b4",
  "brioche-crispy-fried-oyster-mushroom": "c7822f2eb47a77da",
  "brioche-oeuf-florentine": "0e3be3c113fc23b7",
  "cheesy-vegetable-omelette": "8bcc40d8fdafa4a4",
  "sourdough-toast-scrambled-eggs": "9c516186d4484e04",
  "apple-pie": "f669e64bd6ee2602",
  "cheesecake": "487f309cbaf44f03",
  "chocolate-cake": "8c3bd5a0578439e6",
  "fattoush-salad": "31e22a329b8d28a3",
  "caesar-salad": "bd40b8a6e97858dd",
  "shakshuka": "f15fb99ea6e3a7ab",
  "caponata-con-burrata": "ce04605e83254ec3",
  "pita-falafel-with-fries": "8f68e2691a3c52ad",
  "snackplatter": "70ffb77e93f54138",
  "cheese-croquettes-with-mustardmayo": "2b4eae2905b1ad0b",
  "bitterballen-beef-or-veggie": "602a172e08148d85",
  "olives": "50954aced2446616",
  "mixed-nuts": "ba23be0b3801f162",
  "tofu-karaage-with-mayo-and-lemon": "8fe1408c58885b4e",
  "chicken-karaage-with-mayo-and-lemon": "30ff44d560030a36",
  "falafel-balls-with-tahinisauce": "0fad5329b7bb988a",
  "pita-triangles-tzatziki": "c7f3d7babe1ae283",
  "kfc-korean-fried-cauliflower": "a7663c4cb264748e",
  "fries-with-mayonnaise": "0cfbd40681fdd3d9",
  "loaded-nacho-cheese": "56cb4a4838f47183",
  "oeuf-mayonaise": "a43064770c9ae4db",
  "padron-peppers": "667aedb8ffec6e54",
  "caramelized-miso-onions": "7ef13137eb74b626",
  "whole-eggplant-from-the-mibrasa-oven": "3257df4eb1c16b8e",
  "charcoal-roasted-beets": "c4984fb5a8c0c5d6",
  "artichoke-ravioli": "7d33764c0156086b",
  "pulled-mushroom-tacos": "49889e344c463720",
  "gyoza-with-sesame-crispy-chili-oil": "1894b6ce9f827d1f",
  "gnocchi-caccio-e-pepe": "a99410217a58644c",
  "oxheart-cabbage-from-the-mibrasa": "2e623598a8c8dfc7",
  "pita-falafel": "d745ea104af2ef5a",
  "fried-mushroomburger": "c51ace5afcc74dd3",
  "fried-chickenburger": "052372206ded8185",
  "pita-tempeh-badjak": "bbcddd43ef2a1b84",
  "fattoush-salad-2": "11cdf3d621c13267",
  "caesar-salad-2": "7e3097469087f2a9",
  "sourdough-bread-with-miso-honey-butter": "8b589412dcbbeb54",
  "fries-with-mayonnaise-2": "0cfbd40681fdd3d9",
  "sweet-potato-fries-with-srirachamayo": "06d25be5613f547b",
  "cucumber-salad-mint-mustard-seeds": "3cf9e06db17948e4",
  "snackplatter-2": "70ffb77e93f54138",
  "cheese-croquettes-with-mustardmayo-2": "2b4eae2905b1ad0b",
  "bitterballen-beef-or-veggie-2": "602a172e08148d85",
  "olives-2": "50954aced2446616",
  "mixed-nuts-2": "ba23be0b3801f162",
  "tofu-karaage-with-mayo-and-lemon-2": "8fe1408c58885b4e",
  "chicken-karaage-with-mayo-and-lemon-2": "30ff44d560030a36",
  "falafel-balls-with-tahinisauce-2": "0fad5329b7bb988a",
  "pita-triangles-tzatziki-2": "c7f3d7babe1ae283",
  "kfc-korean-fried-cauliflower-2": "bac27bc884615d63",
  "loaded-nacho-cheese-2": "56cb4a4838f47183",
  "rhubarb-apple-crumble": "40911a42e002928f",
  "chocolate-mousse": "acf1a97941d3a4fd",
  "dame-blanche": "03577330cdbdcf11",
  "cheese-plate-from-ten-kate": "4657b739bf46bbd9",
  "table-full": "550fc3a622742243",
  "smoothie-of-the-day": "443e354e94cc2721",
  "soup-of-the-day": "b0062a655fecc60f",
  "coca-cola-regular-or-zero": "832a66e9103da06c",
  "fanta-orange-or-cassis": "8389a90b03087b46",
  "sprite": "5ed7a3e0ab3e8bb9",
  "apple-juice": "81a1b072a8d7a25f",
  "chocomel-fristi": "436ce9eb7620806f",
  "fuze-ice-tea-green-or-lemon": "8ab11720cd90ebb0",
  "chaudfontaine-sparkling-or-still-0-25": "b6403ddcb5d02612",
  "chaudfontaine-sparkling-or-still-0-75": "dd330068d4a37521",
  "finley-ginger-ale": "881bfc0e9dfc5339",
  "big-tom-tomato-juice": "e1ae084347a88455",
  "fresh-orange-juice": "4e0811dba0b50aed",
  "fresh-lemonade-lemon-ginger-or-mint-lime": "2def1f09e94fdc25",
  "homemade-ice-tea-red-fruit-pomegranate-or-classic": "9dc23cf17b4003a6",
  "smoothie-of-the-day-2": "0cffea1c9c25d49f",
  "something-nothing-hibiscus-rose": "b94fda79fa20181e",
  "why-not-raspberry-thyme": "070e8682c89cde3d",
  "why-not-lemon-mate": "bc3f0b99903f747a",
  "cultcha-apple-ginger": "5486d28bdff39251",
  "cultcha-pomegranate-hibiscus": "f7fb5c81c9276e7b",
  "kimino-yuzu": "d9feed033609e47e",
  "coffee-espresso": "657dc5e3191a6a7f",
  "doppio": "7af713f03e667f2f",
  "cappuccino-caffe-latte": "7d8462cc548f42b1",
  "flat-white": "fe41f61134380709",
  "latte-macchiato": "47d7d67030e6046d",
  "espresso-macchiato": "5a8232f798504717",
  "tea": "80667faeedc44420",
  "fresh-mint-or-ginger-tea": "698ba1bf68325d3c",
  "matcha-latte-iced-matcha-latte": "7143f19d6f8deb94",
  "hot-chocolate-whipped-cream-0-5": "50441ba8ca026255",
  "nona-spritz-nona-0-0-spritz-ft-indian-tonic": "160b35dbb063032f",
  "huismus-ginamis-nona-passionfruit-pineapple-soda": "3dfa10f0ff383a49",
  "ginamis-g-t-f-t-indian-tonic-grapefruit-cinnamon": "d9f602d459e3c089",
  "winter-whisky-0-5-field-guide-salt-marsh-peat-cinnamon-syrup": "81f0e60c578c1947",
  "heineken-0-0-pilsener": "4de9610401341a97",
  "erdinger-0-0-weizen-0-5": "a3a120f45ee2e588",
  "funky-falcon-0-2-two-chefs-pale-ale-0-2": "cc5722d3857a7b62",
  "bon-chef-0-5-two-chefs-neipa-0-5": "34d6adccbd4fb5c7",
  "pleno-sud-grillo-sicily-italy": "f6444be3e0f0a75f",
  "bellevaux-chardonnay-pays-d-oc-france": "063e07be8287fd52",
  "rioja-blanco-conde-valdemar-viura-malvasia-tempranillo-blanc": "be18441625f8c070",
  "glup-naranjo-natuurwijn-moscatel-itata-valley-chili": "6defff1c5a4f6b89",
  "valdemoreda-tempranillo-rioja-spain": "5d477c8c1b4f0978",
  "passofino-montepulciano-abruzzo-italie": "08830a3b6c3b083e",
  "rhone-le-petit-maxime-grenache-noir-mourvedre-syrah-cotes-du": "d231604a34172af4",
  "glup-pais-natuurwijn-pais-bio-bio-valley-chili": "482a34c4f6566420",
  "les-petites-cabanes-grenache-languedoc-france": "58d7d52253938de8",
  "pomponette-grenache-syrah-cinsault-couteux-d-aix-en-provence": "cebe42d24b2d934a",
  "torre-del-gall-cava-macabeo-parellada-xarello-penedes-spain": "6d9f07b3bcd1eccd",
  "blancjat-igt-venezia-giulia-frizzante-petnat-100-glere-friul": "506980d01828c6bc",
  "taittinger-chardonnay-pinot-noir-pinot-meunie-champagne-fran": "3166e31d9de992ae",
  "bombay-sapphire-f-t-indian-tonic-lemon-lime": "a91da3627ec2c174",
  "bobby-s-f-t-indian-tonic-orange-cloves": "c0d1236d8796b45d",
  "hendricks-f-t-mediterranean-tonic-cucumber-black-pepper": "9c4af468867ecfc5",
  "mombasa-strawberry-f-t-blueberry-rhubarb-tonic-strawberry-mi": "5f50975a8076b2e5",
  "aperol-spritz-aperol-prosecco-soda-water": "33886c8027595be7",
  "moscow-mule-ketel-1-vodka-gingerbeer-angustura": "ab9f7303e744a350",
  "espresso-martini-vodka-kahlua-espresso": "df13d7f1b266c98a",
  "old-fashioned-bourbon-syrup-bitters": "eeda1b3758dcc8e9",
  "negroni-gin-vermouth-campari": "3ee27369e53b81bc",
  "paloma-tecan-blanco-lime-pink-grapefruit-soda": "4481c40a06e0a9dd",
  "huismus-bombay-sapphire-passionfruit-pineapple-soda": "6b039a63919bdc90",
  "kanarie-martini-plantation-rum-peach-egg-white": "f5dfb8ad0f9f486c",
  "spiced-orange-amaretto-sour-amaretto-makers-mark-orange-juic": "a0cd8f6448eee22a",
  "smokey-margarita-tecan-reposado-tequilla-mezcal-ancho-verde-": "f0882193dd30cf91",
  "hibiscus-sbagliato-campari-sweet-vermouth-hibiscus-syrup-pro": "bc51ac9c9f96eb81",
  "rooibos-cranberry-martini-rooibos-infused-ketel-one-cranberr": "7aa66ff3cf7edf09",
  "yuzu-sake-spritz-yuzu-sake-prosecco-soda-lemon-peel": "3bc3a2f7e37ee235",
  "breakfast-bowl": "9b234c28513c8587",
  "bananabread": "ad07a01adbb7b6bd",
  "fever-tree-gingerbeer": "6a24bee6084e792e"
}